easy_logging/__init__.py
easy_logging/utils.py
iaputes_easy_logging-0.1.dist-info/LICENSE
iaputes_easy_logging-0.1.dist-info/METADATA
iaputes_easy_logging-0.1.dist-info/WHEEL
iaputes_easy_logging-0.1.dist-info/top_level.txt
iaputes_easy_logging-0.1.dist-info/RECORD
