Metadata-Version: 2.1
Name: iaputes_easy_logging
Version: 0.1
Summary: Logging package.
Author-email: Vincent Commere-Ribourg <vincentcommereribourg@gmail.com>
License: Copyright (c) 2018 The Python Packaging Authority
Requires-Python: >=3.7
License-File: LICENSE
Requires-Dist: python-dotenv
